cloudreports/__init__.py
cloudreports/client.py
cloudreports/database.py
cloudreports/functions.py
cloudreports-0.0.8.dist-info/METADATA
cloudreports-0.0.8.dist-info/WHEEL
cloudreports-0.0.8.dist-info/licenses/LICENSE
cloudreports-0.0.8.dist-info/RECORD
