Metadata-Version: 2.4
Name: cloudreports
Version: 0.0.8
Summary: Official Library Cloudreports.ru
Project-URL: Homepage, https://github.com/brmoscow/cloudreports-python
Project-URL: Bug Tracker, https://github.com/brmoscow/cloudreports-python/issues
Author-email: BR Systems <help@cloudreports.ru>
License: GNU GENERAL PUBLIC LICENSE
License-File: LICENSE
Classifier: License :: OSI Approved :: GNU General Public License v3 (GPLv3)
Classifier: Operating System :: OS Independent
Classifier: Programming Language :: Python :: 3
Requires-Python: >=3.7
Requires-Dist: clickhouse-driver
Requires-Dist: google-auth
Requires-Dist: google-auth-httplib2
Requires-Dist: google-auth-oauthlib
Requires-Dist: google-cloud-bigquery
Requires-Dist: pandas
Requires-Dist: requests
